<?xml version="1.0"?>
<!DOCTYPE source_file SYSTEM "apf.v5.1.1.dtd">
<source_file URI="APW_ENG_20030510.0228.sgm" SOURCE="newswire" TYPE="text" AUTHOR="LDC" ENCODING="UTF-8">
<document DOCID="APW_ENG_20030510.0228">
<entity ID="APW_ENG_20030510.0228-E1" TYPE="ORG" SUBTYPE="Media" CLASS="SPC">
  <entity_mention ID="APW_ENG_20030510.0228-E1-2" TYPE="NOM" LDCTYPE="NOM" LDCATR="TRUE">
    <extent>
      <charseq START="714" END="818">a leading
critic of conditions in the south of the country, where a civil war
has been waged for 20 years</charseq>
    </extent>
    <head>
      <charseq START="724" END="729">critic</charseq>
    </head>
  </entity_mention>
  <entity_mention ID="APW_ENG_20030510.0228-E1-7" TYPE="NOM" LDCTYPE="NOM" LDCATR="TRUE">
    <extent>
      <charseq START="832" END="840">the paper</charseq>
    </extent>
    <head>
      <charseq START="836" END="840">paper</charseq>
    </head>
  </entity_mention>
  <entity_mention ID="APW_ENG_20030510.0228-E1-20" TYPE="NOM" LDCTYPE="NOM" LDCATR="TRUE">
    <extent>
      <charseq START="1210" END="1218">the paper</charseq>
    </extent>
    <head>
      <charseq START="1214" END="1218">paper</charseq>
    </head>
  </entity_mention>
  <entity_mention ID="APW_ENG_20030510.0228-E1-23" TYPE="NAM" LDCTYPE="NAM" LDCATR="TRUE">
    <extent>
      <charseq START="1573" END="1583">the Monitor</charseq>
    </extent>
    <head>
      <charseq START="1577" END="1583">Monitor</charseq>
    </head>
  </entity_mention>
  <entity_mention ID="APW_ENG_20030510.0228-E1-31" TYPE="NAM" LDCTYPE="NAM" LDCATR="TRUE">
    <extent>
      <charseq START="1834" END="1844">the Monitor</charseq>
    </extent>
    <head>
      <charseq START="1838" END="1844">Monitor</charseq>
    </head>
  </entity_mention>
  <entity_mention ID="APW_ENG_20030510.0228-E1-33" TYPE="PRO" LDCTYPE="PRO" LDCATR="TRUE">
    <extent>
      <charseq START="1874" END="1876">its</charseq>
    </extent>
    <head>
      <charseq START="1874" END="1876">its</charseq>
    </head>
  </entity_mention>
  <entity_mention ID="APW_ENG_20030510.0228-E1-35" TYPE="PRO" LDCTYPE="PRO" LDCATR="TRUE">
    <extent>
      <charseq START="1943" END="1944">it</charseq>
    </extent>
    <head>
      <charseq START="1943" END="1944">it</charseq>
    </head>
  </entity_mention>
  <entity_mention ID="APW_ENG_20030510.0228-E1-36" TYPE="PRO" LDCTYPE="PRO" LDCATR="TRUE">
    <extent>
      <charseq START="1969" END="1970">it</charseq>
    </extent>
    <head>
      <charseq START="1969" END="1970">it</charseq>
    </head>
  </entity_mention>
  <entity_mention ID="APW_ENG_20030510.0228-E1-38" TYPE="NAM" LDCTYPE="NAM" LDCATR="TRUE">
    <extent>
      <charseq START="2088" END="2098">The Monitor</charseq>
    </extent>
    <head>
      <charseq START="2092" END="2098">Monitor</charseq>
    </head>
  </entity_mention>
  <entity_mention ID="APW_ENG_20030510.0228-E1-39" TYPE="PRO" LDCTYPE="PRO" LDCATR="TRUE">
    <extent>
      <charseq START="2126" END="2128">its</charseq>
    </extent>
    <head>
      <charseq START="2126" END="2128">its</charseq>
    </head>
  </entity_mention>
  <entity_mention ID="APW_ENG_20030510.0228-E1-41" TYPE="NOM" LDCTYPE="NOM" LDCATR="TRUE">
    <extent>
      <charseq START="2174" END="2182">the paper</charseq>
    </extent>
    <head>
      <charseq START="2178" END="2182">paper</charseq>
    </head>
  </entity_mention>
  <entity_mention ID="APW_ENG_20030510.0228-E1-56" TYPE="PRO" LDCTYPE="PRO" LDCATR="TRUE">
    <extent>
      <charseq START="865" END="866">it</charseq>
    </extent>
    <head>
      <charseq START="865" END="866">it</charseq>
    </head>
  </entity_mention>
  <entity_mention ID="APW_ENG_20030510.0228-E1-60" TYPE="NOM" LDCTYPE="NOM" LDCATR="TRUE">
    <extent>
      <charseq START="196" END="233">a newspaper critical of the
government</charseq>
    </extent>
    <head>
      <charseq START="198" END="206">newspaper</charseq>
    </head>
  </entity_mention>
  <entity_mention ID="APW_ENG_20030510.0228-E1-61" TYPE="PRO" LDCTYPE="PRO" LDCATR="TRUE">
    <extent>
      <charseq START="261" END="262">it</charseq>
    </extent>
    <head>
      <charseq START="261" END="262">it</charseq>
    </head>
  </entity_mention>
  <entity_mention ID="APW_ENG_20030510.0228-E1-62" TYPE="NOM" LDCTYPE="NOM" LDCATR="TRUE">
    <extent>
      <charseq START="313" END="325">the newspaper</charseq>
    </extent>
    <head>
      <charseq START="317" END="325">newspaper</charseq>
    </head>
  </entity_mention>
  <entity_mention ID="APW_ENG_20030510.0228-E1-63" TYPE="NAM" LDCTYPE="NAM" LDCATR="TRUE">
    <extent>
      <charseq START="343" END="362">The Khartoum Monitor</charseq>
    </extent>
    <head>
      <charseq START="347" END="362">Khartoum Monitor</charseq>
    </head>
  </entity_mention>
  <entity_mention ID="APW_ENG_20030510.0228-E1-67" TYPE="NAM" LDCTYPE="NAM" LDCATR="TRUE">
    <extent>
      <charseq START="656" END="666">the
Monitor</charseq>
    </extent>
    <head>
      <charseq START="660" END="666">Monitor</charseq>
    </head>
  </entity_mention>
  <entity_mention ID="APW_ENG_20030510.0228-E1-68" TYPE="NOM" LDCTYPE="NOM" LDCATR="TRUE" METONYMY_MENTION="TRUE">
    <extent>
      <charseq START="669" END="708">the only English language daily in Sudan</charseq>
    </extent>
    <head>
      <charseq START="695" END="699">daily</charseq>
    </head>
  </entity_mention>
  <entity_attributes>
    <name NAME="Monitor">
      <charseq START="1577" END="1583">Monitor</charseq>
    </name>
    <name NAME="Monitor">
      <charseq START="1838" END="1844">Monitor</charseq>
    </name>
    <name NAME="Monitor">
      <charseq START="2092" END="2098">Monitor</charseq>
    </name>
    <name NAME="Khartoum Monitor">
      <charseq START="347" END="362">Khartoum Monitor</charseq>
    </name>
    <name NAME="Monitor">
      <charseq START="660" END="666">Monitor</charseq>
    </name>
  </entity_attributes>
</entity>
<entity ID="APW_ENG_20030510.0228-E2" TYPE="LOC" SUBTYPE="Region-General" CLASS="SPC">
  <entity_mention ID="APW_ENG_20030510.0228-E2-3" TYPE="NOM" LDCTYPE="NOM">
    <extent>
      <charseq START="748" END="818">the south of the country, where a civil war
has been waged for 20 years</charseq>
    </extent>
    <head>
      <charseq START="752" END="756">south</charseq>
    </head>
  </entity_mention>
  <entity_mention ID="APW_ENG_20030510.0228-E2-5" TYPE="PRO" LDCTYPE="WHQ">
    <extent>
      <charseq START="774" END="778">where</charseq>
    </extent>
    <head>
      <charseq START="774" END="778">where</charseq>
    </head>
  </entity_mention>
</entity>
<entity ID="APW_ENG_20030510.0228-E3" TYPE="ORG" SUBTYPE="Government" CLASS="SPC">
  <entity_mention ID="APW_ENG_20030510.0228-E3-9" TYPE="NOM" LDCTYPE="NOMPRE" LDCATR="TRUE">
    <extent>
      <charseq START="904" END="908">court</charseq>
    </extent>
    <head>
      <charseq START="904" END="908">court</charseq>
    </head>
  </entity_mention>
  <entity_mention ID="APW_ENG_20030510.0228-E3-19" TYPE="NOM" LDCTYPE="NOM" LDCATR="FALSE">
    <extent>
      <charseq START="1190" END="1198">The court</charseq>
    </extent>
    <head>
      <charseq START="1194" END="1198">court</charseq>
    </head>
  </entity_mention>
  <entity_mention ID="APW_ENG_20030510.0228-E3-59" TYPE="NOM" LDCTYPE="NOM" LDCATR="FALSE">
    <extent>
      <charseq START="163" END="184">A state security court</charseq>
    </extent>
    <head>
      <charseq START="180" END="184">court</charseq>
    </head>
  </entity_mention>
</entity>
<entity ID="APW_ENG_20030510.0228-E4" TYPE="ORG" SUBTYPE="Government" CLASS="SPC">
  <entity_mention ID="APW_ENG_20030510.0228-E4-10" TYPE="NAM" LDCTYPE="NAM" LDCATR="FALSE">
    <extent>
      <charseq START="976" END="1001">the National Press Council</charseq>
    </extent>
    <head>
      <charseq START="980" END="1001">National Press Council</charseq>
    </head>
  </entity_mention>
  <entity_mention ID="APW_ENG_20030510.0228-E4-11" TYPE="NOM" LDCTYPE="NOM" LDCATR="TRUE">
    <extent>
      <charseq START="1004" END="1030">a government-appointed body</charseq>
    </extent>
    <head>
      <charseq START="1027" END="1030">body</charseq>
    </head>
  </entity_mention>
  <entity_mention ID="APW_ENG_20030510.0228-E4-15" TYPE="NAM" LDCTYPE="NAM" LDCATR="FALSE">
    <extent>
      <charseq START="1084" END="1109">the National Press Council</charseq>
    </extent>
    <head>
      <charseq START="1088" END="1109">National Press Council</charseq>
    </head>
  </entity_mention>
  <entity_attributes>
    <name NAME="National Press Council">
      <charseq START="980" END="1001">National Press Council</charseq>
    </name>
    <name NAME="National Press Council">
      <charseq START="1088" END="1109">National Press Council</charseq>
    </name>
  </entity_attributes>
</entity>
<entity ID="APW_ENG_20030510.0228-E6" TYPE="PER" SUBTYPE="Individual" CLASS="SPC">
  <entity_mention ID="APW_ENG_20030510.0228-E6-14" TYPE="NOM" LDCTYPE="NOM" LDCATR="FALSE">
    <extent>
      <charseq START="1059" END="1109">The secretary general of the National Press Council</charseq>
    </extent>
    <head>
      <charseq START="1063" END="1071">secretary</charseq>
    </head>
  </entity_mention>
  <entity_mention ID="APW_ENG_20030510.0228-E6-16" TYPE="NAM" LDCTYPE="NAM" LDCATR="TRUE">
    <extent>
      <charseq START="1112" END="1125">Hashim el-Jazz</charseq>
    </extent>
    <head>
      <charseq START="1112" END="1125">Hashim el-Jazz</charseq>
    </head>
  </entity_mention>
  <entity_mention ID="APW_ENG_20030510.0228-E6-18" TYPE="PRO" LDCTYPE="PRO" LDCATR="FALSE">
    <extent>
      <charseq START="1161" END="1163">his</charseq>
    </extent>
    <head>
      <charseq START="1161" END="1163">his</charseq>
    </head>
  </entity_mention>
  <entity_attributes>
    <name NAME="Hashim el-Jazz">
      <charseq START="1112" END="1125">Hashim el-Jazz</charseq>
    </name>
  </entity_attributes>
</entity>
<entity ID="APW_ENG_20030510.0228-E8" TYPE="PER" SUBTYPE="Individual" CLASS="SPC">
  <entity_mention ID="APW_ENG_20030510.0228-E8-21" TYPE="NOM" LDCTYPE="NOM">
    <extent>
      <charseq START="1409" END="1418">the-editor</charseq>
    </extent>
    <head>
      <charseq START="1413" END="1418">editor</charseq>
    </head>
  </entity_mention>
</entity>
<entity ID="APW_ENG_20030510.0228-E9" TYPE="PER" SUBTYPE="Group" CLASS="USP">
  <entity_mention ID="APW_ENG_20030510.0228-E9-22" TYPE="NOM" LDCTYPE="BAR">
    <extent>
      <charseq START="1548" END="1562">security police</charseq>
    </extent>
    <head>
      <charseq START="1557" END="1562">police</charseq>
    </head>
  </entity_mention>
</entity>
<entity ID="APW_ENG_20030510.0228-E10" TYPE="PER" SUBTYPE="Individual" CLASS="SPC">
  <entity_mention ID="APW_ENG_20030510.0228-E10-24" TYPE="NOM" LDCTYPE="NOM" LDCATR="FALSE">
    <extent>
      <charseq START="1573" END="1601">the Monitor's managing
editor</charseq>
    </extent>
    <head>
      <charseq START="1596" END="1601">editor</charseq>
    </head>
  </entity_mention>
  <entity_mention ID="APW_ENG_20030510.0228-E10-25" TYPE="NAM" LDCTYPE="NAM" LDCATR="TRUE">
    <extent>
      <charseq START="1604" END="1612">Nhial Bol</charseq>
    </extent>
    <head>
      <charseq START="1604" END="1612">Nhial Bol</charseq>
    </head>
  </entity_mention>
  <entity_mention ID="APW_ENG_20030510.0228-E10-27" TYPE="PRO" LDCTYPE="PRO" LDCATR="FALSE">
    <extent>
      <charseq START="1632" END="1634">his</charseq>
    </extent>
    <head>
      <charseq START="1632" END="1634">his</charseq>
    </head>
  </entity_mention>
  <entity_mention ID="APW_ENG_20030510.0228-E10-28" TYPE="PRO" LDCTYPE="PRO" LDCATR="FALSE">
    <extent>
      <charseq START="1645" END="1646">he</charseq>
    </extent>
    <head>
      <charseq START="1645" END="1646">he</charseq>
    </head>
  </entity_mention>
  <entity_attributes>
    <name NAME="Nhial Bol">
      <charseq START="1604" END="1612">Nhial Bol</charseq>
    </name>
  </entity_attributes>
</entity>
<entity ID="APW_ENG_20030510.0228-E12" TYPE="PER" SUBTYPE="Group" CLASS="USP">
  <entity_mention ID="APW_ENG_20030510.0228-E12-30" TYPE="NOM" LDCTYPE="NOM">
    <extent>
      <charseq START="1770" END="1801">a substantial
Christian minority</charseq>
    </extent>
    <head>
      <charseq START="1794" END="1801">minority</charseq>
    </head>
  </entity_mention>
</entity>
<entity ID="APW_ENG_20030510.0228-E13" TYPE="PER" SUBTYPE="Group" CLASS="USP">
  <entity_mention ID="APW_ENG_20030510.0228-E13-32" TYPE="NOM" LDCTYPE="BAR">
    <extent>
      <charseq START="1847" END="1864">security officials</charseq>
    </extent>
    <head>
      <charseq START="1856" END="1864">officials</charseq>
    </head>
  </entity_mention>
</entity>
<entity ID="APW_ENG_20030510.0228-E14" TYPE="FAC" SUBTYPE="Subarea-Facility" CLASS="SPC">
  <entity_mention ID="APW_ENG_20030510.0228-E14-34" TYPE="NOM" LDCTYPE="NOM">
    <extent>
      <charseq START="1874" END="1894">its editorial offices</charseq>
    </extent>
    <head>
      <charseq START="1888" END="1894">offices</charseq>
    </head>
  </entity_mention>
  <entity_mention ID="APW_ENG_20030510.0228-E14-40" TYPE="NOM" LDCTYPE="NOM">
    <extent>
      <charseq START="2126" END="2136">its offices</charseq>
    </extent>
    <head>
      <charseq START="2130" END="2136">offices</charseq>
    </head>
  </entity_mention>
</entity>
<entity ID="APW_ENG_20030510.0228-E15" TYPE="ORG" SUBTYPE="Government" CLASS="GEN">
  <entity_mention ID="APW_ENG_20030510.0228-E15-37" TYPE="NOM" LDCTYPE="NOMPRE">
    <extent>
      <charseq START="2059" END="2063">court</charseq>
    </extent>
    <head>
      <charseq START="2059" END="2063">court</charseq>
    </head>
  </entity_mention>
</entity>
<entity ID="APW_ENG_20030510.0228-E16" TYPE="VEH" SUBTYPE="Land" CLASS="USP">
  <entity_mention ID="APW_ENG_20030510.0228-E16-42" TYPE="NOM" LDCTYPE="BAR">
    <extent>
      <charseq START="2245" END="2285">trains running to and from southern
Sudan</charseq>
    </extent>
    <head>
      <charseq START="2245" END="2250">trains</charseq>
    </head>
  </entity_mention>
</entity>
<entity ID="APW_ENG_20030510.0228-E17" TYPE="GPE" SUBTYPE="Population-Center" CLASS="SPC">
  <entity_mention ID="APW_ENG_20030510.0228-E17-1" TYPE="NAM" LDCTYPE="NAM" ROLE="LOC">
    <extent>
      <charseq START="141" END="155">KHARTOUM, Sudan</charseq>
    </extent>
    <head>
      <charseq START="141" END="148">KHARTOUM</charseq>
    </head>
  </entity_mention>
  <entity_attributes>
    <name NAME="KHARTOUM">
      <charseq START="141" END="148">KHARTOUM</charseq>
    </name>
  </entity_attributes>
</entity>
<entity ID="APW_ENG_20030510.0228-E18" TYPE="LOC" SUBTYPE="Region-General" CLASS="SPC">
  <entity_mention ID="APW_ENG_20030510.0228-E18-43" TYPE="NOM" LDCTYPE="BAR">
    <extent>
      <charseq START="2272" END="2285">southern
Sudan</charseq>
    </extent>
    <head>
      <charseq START="2281" END="2285">Sudan</charseq>
    </head>
  </entity_mention>
</entity>
<entity ID="APW_ENG_20030510.0228-E19" TYPE="PER" SUBTYPE="Group" CLASS="USP">
  <entity_mention ID="APW_ENG_20030510.0228-E19-44" TYPE="NOM" LDCTYPE="BAR">
    <extent>
      <charseq START="2310" END="2336">abducted women and children</charseq>
    </extent>
    <head>
      <charseq START="2319" END="2323">women</charseq>
    </head>
  </entity_mention>
</entity>
<entity ID="APW_ENG_20030510.0228-E20" TYPE="PER" SUBTYPE="Group" CLASS="USP">
  <entity_mention ID="APW_ENG_20030510.0228-E20-45" TYPE="NOM" LDCTYPE="BAR">
    <extent>
      <charseq START="2310" END="2336">abducted women and children</charseq>
    </extent>
    <head>
      <charseq START="2329" END="2336">children</charseq>
    </head>
  </entity_mention>
</entity>
<entity ID="APW_ENG_20030510.0228-E21" TYPE="PER" SUBTYPE="Group" CLASS="USP">
  <entity_mention ID="APW_ENG_20030510.0228-E21-47" TYPE="NOM" LDCTYPE="NOM">
    <extent>
      <charseq START="1923" END="1936">the management</charseq>
    </extent>
    <head>
      <charseq START="1927" END="1936">management</charseq>
    </head>
  </entity_mention>
</entity>
<entity ID="APW_ENG_20030510.0228-E22" TYPE="GPE" SUBTYPE="Nation" CLASS="SPC">
  <entity_mention ID="APW_ENG_20030510.0228-E22-4" TYPE="NOM" LDCTYPE="NOM" ROLE="LOC" LDCATR="FALSE">
    <extent>
      <charseq START="761" END="771">the country</charseq>
    </extent>
    <head>
      <charseq START="765" END="771">country</charseq>
    </head>
  </entity_mention>
  <entity_mention ID="APW_ENG_20030510.0228-E22-29" TYPE="NAM" LDCTYPE="NAM" ROLE="GPE" LDCATR="FALSE">
    <extent>
      <charseq START="1723" END="1727">Sudan</charseq>
    </extent>
    <head>
      <charseq START="1723" END="1727">Sudan</charseq>
    </head>
  </entity_mention>
  <entity_mention ID="APW_ENG_20030510.0228-E22-46" TYPE="NAM" LDCTYPE="NAM" ROLE="LOC" LDCATR="FALSE">
    <extent>
      <charseq START="151" END="155">Sudan</charseq>
    </extent>
    <head>
      <charseq START="151" END="155">Sudan</charseq>
    </head>
  </entity_mention>
  <entity_mention ID="APW_ENG_20030510.0228-E22-48" TYPE="NOM" LDCTYPE="NOMPRE" ROLE="GPE" LDCATR="TRUE">
    <extent>
      <charseq START="165" END="169">state</charseq>
    </extent>
    <head>
      <charseq START="165" END="169">state</charseq>
    </head>
  </entity_mention>
  <entity_mention ID="APW_ENG_20030510.0228-E22-49" TYPE="NOM" LDCTYPE="NOMPRE" ROLE="GPE" LDCATR="TRUE">
    <extent>
      <charseq START="634" END="638">state</charseq>
    </extent>
    <head>
      <charseq START="634" END="638">state</charseq>
    </head>
  </entity_mention>
  <entity_mention ID="APW_ENG_20030510.0228-E22-50" TYPE="NOM" LDCTYPE="NOMPRE" ROLE="GPE" LDCATR="TRUE">
    <extent>
      <charseq START="1006" END="1015">government</charseq>
    </extent>
    <head>
      <charseq START="1006" END="1015">government</charseq>
    </head>
  </entity_mention>
  <entity_mention ID="APW_ENG_20030510.0228-E22-51" TYPE="NOM" LDCTYPE="NOM" ROLE="ORG" LDCATR="FALSE">
    <extent>
      <charseq START="1733" END="1764">an Islamic-orientated government</charseq>
    </extent>
    <head>
      <charseq START="1755" END="1764">government</charseq>
    </head>
  </entity_mention>
  <entity_mention ID="APW_ENG_20030510.0228-E22-52" TYPE="NOM" LDCTYPE="NOM" ROLE="ORG" LDCATR="FALSE">
    <extent>
      <charseq START="2210" END="2223">the
government</charseq>
    </extent>
    <head>
      <charseq START="2214" END="2223">government</charseq>
    </head>
  </entity_mention>
  <entity_mention ID="APW_ENG_20030510.0228-E22-53" TYPE="NOM" LDCTYPE="NOM" ROLE="ORG" LDCATR="FALSE">
    <extent>
      <charseq START="220" END="233">the
government</charseq>
    </extent>
    <head>
      <charseq START="224" END="233">government</charseq>
    </head>
  </entity_mention>
  <entity_mention ID="APW_ENG_20030510.0228-E22-54" TYPE="NAM" LDCTYPE="NAMPRE" ROLE="GPE" LDCATR="TRUE">
    <extent>
      <charseq START="427" END="434">Sudanese</charseq>
    </extent>
    <head>
      <charseq START="427" END="434">Sudanese</charseq>
    </head>
  </entity_mention>
  <entity_mention ID="APW_ENG_20030510.0228-E22-55" TYPE="NAM" LDCTYPE="NAMPRE" ROLE="GPE" LDCATR="TRUE">
    <extent>
      <charseq START="1998" END="2005">Sudanese</charseq>
    </extent>
    <head>
      <charseq START="1998" END="2005">Sudanese</charseq>
    </head>
  </entity_mention>
  <entity_mention ID="APW_ENG_20030510.0228-E22-70" TYPE="NAM" LDCTYPE="NAM" ROLE="LOC" LDCATR="FALSE">
    <extent>
      <charseq START="704" END="708">Sudan</charseq>
    </extent>
    <head>
      <charseq START="704" END="708">Sudan</charseq>
    </head>
  </entity_mention>
  <entity_attributes>
    <name NAME="Sudan">
      <charseq START="1723" END="1727">Sudan</charseq>
    </name>
    <name NAME="Sudan">
      <charseq START="151" END="155">Sudan</charseq>
    </name>
    <name NAME="Sudanese">
      <charseq START="427" END="434">Sudanese</charseq>
    </name>
    <name NAME="Sudanese">
      <charseq START="1998" END="2005">Sudanese</charseq>
    </name>
    <name NAME="Sudan">
      <charseq START="704" END="708">Sudan</charseq>
    </name>
  </entity_attributes>
</entity>
<entity ID="APW_ENG_20030510.0228-E27" TYPE="PER" SUBTYPE="Group" CLASS="GEN">
  <entity_mention ID="APW_ENG_20030510.0228-E27-57" TYPE="NOM" LDCTYPE="NOMPRE">
    <extent>
      <charseq START="1784" END="1792">Christian</charseq>
    </extent>
    <head>
      <charseq START="1784" END="1792">Christian</charseq>
    </head>
  </entity_mention>
</entity>
<entity ID="APW_ENG_20030510.0228-E29" TYPE="ORG" SUBTYPE="Media" CLASS="SPC">
  <entity_mention ID="APW_ENG_20030510.0228-E29-58" TYPE="NAM" LDCTYPE="NAM">
    <extent>
      <charseq START="158" END="159">AP</charseq>
    </extent>
    <head>
      <charseq START="158" END="159">AP</charseq>
    </head>
  </entity_mention>
  <entity_mention ID="APW_ENG_20030510.0228-E29-66" TYPE="NAM" LDCTYPE="NAM">
    <extent>
      <charseq START="487" END="506">The Associated Press</charseq>
    </extent>
    <head>
      <charseq START="491" END="506">Associated Press</charseq>
    </head>
  </entity_mention>
  <entity_attributes>
    <name NAME="AP">
      <charseq START="158" END="159">AP</charseq>
    </name>
    <name NAME="Associated Press">
      <charseq START="491" END="506">Associated Press</charseq>
    </name>
  </entity_attributes>
</entity>
<entity ID="APW_ENG_20030510.0228-E32" TYPE="PER" SUBTYPE="Individual" CLASS="SPC">
  <entity_mention ID="APW_ENG_20030510.0228-E32-6" TYPE="NAM" LDCTYPE="NAM" LDCATR="FALSE">
    <extent>
      <charseq START="822" END="825">Ngor</charseq>
    </extent>
    <head>
      <charseq START="822" END="825">Ngor</charseq>
    </head>
  </entity_mention>
  <entity_mention ID="APW_ENG_20030510.0228-E32-8" TYPE="NOM" LDCTYPE="NOM" LDCATR="FALSE">
    <extent>
      <charseq START="313" END="334">the newspaper's lawyer</charseq>
    </extent>
    <head>
      <charseq START="329" END="334">lawyer</charseq>
    </head>
  </entity_mention>
  <entity_mention ID="APW_ENG_20030510.0228-E32-13" TYPE="NAM" LDCTYPE="NAM" LDCATR="FALSE">
    <extent>
      <charseq START="1047" END="1050">Ngor</charseq>
    </extent>
    <head>
      <charseq START="1047" END="1050">Ngor</charseq>
    </head>
  </entity_mention>
  <entity_mention ID="APW_ENG_20030510.0228-E32-64" TYPE="NOM" LDCTYPE="NOMPRE" LDCATR="TRUE">
    <extent>
      <charseq START="459" END="464">lawyer</charseq>
    </extent>
    <head>
      <charseq START="459" END="464">lawyer</charseq>
    </head>
  </entity_mention>
  <entity_mention ID="APW_ENG_20030510.0228-E32-65" TYPE="NAM" LDCTYPE="NAM" LDCATR="FALSE">
    <extent>
      <charseq START="459" END="480">lawyer Ngor Olang
Ngor</charseq>
    </extent>
    <head>
      <charseq START="466" END="480">Ngor Olang
Ngor</charseq>
    </head>
  </entity_mention>
  <entity_attributes>
    <name NAME="Ngor">
      <charseq START="822" END="825">Ngor</charseq>
    </name>
    <name NAME="Ngor">
      <charseq START="1047" END="1050">Ngor</charseq>
    </name>
    <name NAME="Ngor Olang Ngor">
      <charseq START="466" END="480">Ngor Olang
Ngor</charseq>
    </name>
  </entity_attributes>
</entity>
<value ID="APW_ENG_20030510.0228-V1" TYPE="Numeric" SUBTYPE="Money">
  <value_mention ID="APW_ENG_20030510.0228-V1-1">
    <extent>
      <charseq START="417" END="441">1 million Sudanese pounds</charseq>
    </extent>
  </value_mention>
</value>
<value ID="APW_ENG_20030510.0228-V2" TYPE="Numeric" SUBTYPE="Money">
  <value_mention ID="APW_ENG_20030510.0228-V2-1">
    <extent>
      <charseq START="444" END="455">about US$400</charseq>
    </extent>
  </value_mention>
</value>
<value ID="APW_ENG_20030510.0228-V3" TYPE="Numeric" SUBTYPE="Money">
  <value_mention ID="APW_ENG_20030510.0228-V3-1">
    <extent>
      <charseq START="1987" END="2012">15 million Sudanese
pounds</charseq>
    </extent>
  </value_mention>
</value>
<value ID="APW_ENG_20030510.0228-V4" TYPE="Numeric" SUBTYPE="Money">
  <value_mention ID="APW_ENG_20030510.0228-V4-1">
    <extent>
      <charseq START="2015" END="2028">about US$6,000</charseq>
    </extent>
  </value_mention>
</value>
<value ID="APW_ENG_20030510.0228-V5" TYPE="Crime">
  <value_mention ID="APW_ENG_20030510.0228-V5-1">
    <extent>
      <charseq START="1665" END="1692">incitement of public discord</charseq>
    </extent>
  </value_mention>
</value>
<value ID="APW_ENG_20030510.0228-V6" TYPE="Crime">
  <value_mention ID="APW_ENG_20030510.0228-V6-1">
    <extent>
      <charseq START="2201" END="2223">defaming the
government</charseq>
    </extent>
  </value_mention>
</value>
<value ID="APW_ENG_20030510.0228-V7" TYPE="Crime">
  <value_mention ID="APW_ENG_20030510.0228-V7-1">
    <extent>
      <charseq START="267" END="310">publishing religiously
inflammatory material</charseq>
    </extent>
  </value_mention>
</value>
<value ID="APW_ENG_20030510.0228-V8" TYPE="Crime">
  <value_mention ID="APW_ENG_20030510.0228-V8-1">
    <extent>
      <charseq START="1223" END="1259">violating article 25 of the Press
Law</charseq>
    </extent>
  </value_mention>
</value>
<timex2 ID="APW_ENG_20030510.0228-T1" VAL="P2M" ANCHOR_VAL="2003-07-10" ANCHOR_DIR="STARTING">
  <timex2_mention ID="APW_ENG_20030510.0228-T1-1">
    <extent>
      <charseq START="551" END="559">two-month</charseq>
    </extent>
  </timex2_mention>
</timex2>
<timex2 ID="APW_ENG_20030510.0228-T2" VAL="P20Y" ANCHOR_VAL="1983" ANCHOR_DIR="STARTING">
  <timex2_mention ID="APW_ENG_20030510.0228-T2-1">
    <extent>
      <charseq START="811" END="818">20 years</charseq>
    </extent>
  </timex2_mention>
</timex2>
<timex2 ID="APW_ENG_20030510.0228-T3" VAL="2003-05-10">
  <timex2_mention ID="APW_ENG_20030510.0228-T3-1">
    <extent>
      <charseq START="1179" END="1186">Saturday</charseq>
    </extent>
  </timex2_mention>
</timex2>
<timex2 ID="APW_ENG_20030510.0228-T4" VAL="2003-04">
  <timex2_mention ID="APW_ENG_20030510.0228-T4-1">
    <extent>
      <charseq START="1430" END="1439">last month</charseq>
    </extent>
  </timex2_mention>
</timex2>
<timex2 ID="APW_ENG_20030510.0228-T5" VAL="2003-W19">
  <timex2_mention ID="APW_ENG_20030510.0228-T5-1">
    <extent>
      <charseq START="1529" END="1545">Earlier this week</charseq>
    </extent>
  </timex2_mention>
</timex2>
<timex2 ID="APW_ENG_20030510.0228-T6" VAL="PT24H" ANCHOR_VAL="2003-W19" ANCHOR_DIR="WITHIN">
  <timex2_mention ID="APW_ENG_20030510.0228-T6-1">
    <extent>
      <charseq START="1619" END="1626">24 hours</charseq>
    </extent>
  </timex2_mention>
</timex2>
<timex2 ID="APW_ENG_20030510.0228-T7" VAL="2003-05-08TNI">
  <timex2_mention ID="APW_ENG_20030510.0228-T7-1">
    <extent>
      <charseq START="1899" END="1912">Thursday night</charseq>
    </extent>
  </timex2_mention>
</timex2>
<timex2 ID="APW_ENG_20030510.0228-T8" VAL="2002">
  <timex2_mention ID="APW_ENG_20030510.0228-T8-1">
    <extent>
      <charseq START="2076" END="2084">last year</charseq>
    </extent>
  </timex2_mention>
</timex2>
<timex2 ID="APW_ENG_20030510.0228-T9" VAL="2003-05-09">
  <timex2_mention ID="APW_ENG_20030510.0228-T9-1">
    <extent>
      <charseq START="2115" END="2120">Friday</charseq>
    </extent>
  </timex2_mention>
</timex2>
<timex2 ID="APW_ENG_20030510.0228-T10" VAL="2002">
  <timex2_mention ID="APW_ENG_20030510.0228-T10-1">
    <extent>
      <charseq START="2155" END="2163">last year</charseq>
    </extent>
  </timex2_mention>
</timex2>
<timex2 ID="APW_ENG_20030510.0228-T11" VAL="2003-05-10">
  <timex2_mention ID="APW_ENG_20030510.0228-T11-1">
    <extent>
      <charseq START="39" END="46">20030510</charseq>
    </extent>
  </timex2_mention>
</timex2>
<timex2 ID="APW_ENG_20030510.0228-T12" VAL="XXXX-XX-XX" SET="YES">
  <timex2_mention ID="APW_ENG_20030510.0228-T12-1">
    <extent>
      <charseq START="695" END="699">daily</charseq>
    </extent>
  </timex2_mention>
</timex2>
<timex2 ID="APW_ENG_20030510.0228-T13" VAL="2003-05-10">
  <timex2_mention ID="APW_ENG_20030510.0228-T13-1">
    <extent>
      <charseq START="235" END="242">Saturday</charseq>
    </extent>
  </timex2_mention>
</timex2>
<timex2 ID="APW_ENG_20030510.0228-T14" VAL="P2M" ANCHOR_VAL="2003-05-10" ANCHOR_DIR="STARTING">
  <timex2_mention ID="APW_ENG_20030510.0228-T14-1">
    <extent>
      <charseq START="383" END="392">two months</charseq>
    </extent>
  </timex2_mention>
</timex2>
<relation ID="APW_ENG_20030510.0228-R1" TYPE="PART-WHOLE" SUBTYPE="Geographical" TENSE="Unspecified" MODALITY="Asserted">
  <relation_argument REFID="APW_ENG_20030510.0228-E17" ROLE="Arg-1"/>
  <relation_argument REFID="APW_ENG_20030510.0228-E22" ROLE="Arg-2"/>
  <relation_mention ID="APW_ENG_20030510.0228-R1-1" LEXICALCONDITION="Formulaic">
    <extent>
      <charseq START="141" END="155">KHARTOUM, Sudan</charseq>
    </extent>
    <relation_mention_argument REFID="APW_ENG_20030510.0228-E17-1" ROLE="Arg-1">
      <extent>
        <charseq START="141" END="155">KHARTOUM, Sudan</charseq>
      </extent>
    </relation_mention_argument>
    <relation_mention_argument REFID="APW_ENG_20030510.0228-E22-46" ROLE="Arg-2">
      <extent>
        <charseq START="151" END="155">Sudan</charseq>
      </extent>
    </relation_mention_argument>
  </relation_mention>
</relation>
<relation ID="APW_ENG_20030510.0228-R2" TYPE="PART-WHOLE" SUBTYPE="Subsidiary" TENSE="Unspecified" MODALITY="Asserted">
  <relation_argument REFID="APW_ENG_20030510.0228-E3" ROLE="Arg-1"/>
  <relation_argument REFID="APW_ENG_20030510.0228-E22" ROLE="Arg-2"/>
  <relation_mention ID="APW_ENG_20030510.0228-R2-1" LEXICALCONDITION="PreMod">
    <extent>
      <charseq START="163" END="184">A state security court</charseq>
    </extent>
    <relation_mention_argument REFID="APW_ENG_20030510.0228-E3-59" ROLE="Arg-1">
      <extent>
        <charseq START="163" END="184">A state security court</charseq>
      </extent>
    </relation_mention_argument>
    <relation_mention_argument REFID="APW_ENG_20030510.0228-E22-48" ROLE="Arg-2">
      <extent>
        <charseq START="165" END="169">state</charseq>
      </extent>
    </relation_mention_argument>
  </relation_mention>
</relation>
<relation ID="APW_ENG_20030510.0228-R4" TYPE="ORG-AFF" SUBTYPE="Employment" TENSE="Unspecified" MODALITY="Asserted">
  <relation_argument REFID="APW_ENG_20030510.0228-E32" ROLE="Arg-1"/>
  <relation_argument REFID="APW_ENG_20030510.0228-E1" ROLE="Arg-2"/>
  <relation_mention ID="APW_ENG_20030510.0228-R4-1" LEXICALCONDITION="Possessive">
    <extent>
      <charseq START="313" END="334">the newspaper's lawyer</charseq>
    </extent>
    <relation_mention_argument REFID="APW_ENG_20030510.0228-E32-8" ROLE="Arg-1">
      <extent>
        <charseq START="313" END="334">the newspaper's lawyer</charseq>
      </extent>
    </relation_mention_argument>
    <relation_mention_argument REFID="APW_ENG_20030510.0228-E1-62" ROLE="Arg-2">
      <extent>
        <charseq START="313" END="325">the newspaper</charseq>
      </extent>
    </relation_mention_argument>
  </relation_mention>
</relation>
<relation ID="APW_ENG_20030510.0228-R5" TYPE="PART-WHOLE" SUBTYPE="Geographical" TENSE="Unspecified" MODALITY="Asserted">
  <relation_argument REFID="APW_ENG_20030510.0228-E2" ROLE="Arg-1"/>
  <relation_argument REFID="APW_ENG_20030510.0228-E22" ROLE="Arg-2"/>
  <relation_mention ID="APW_ENG_20030510.0228-R5-1" LEXICALCONDITION="Preposition">
    <extent>
      <charseq START="748" END="818">the south of the country, where a civil war
has been waged for 20 years</charseq>
    </extent>
    <relation_mention_argument REFID="APW_ENG_20030510.0228-E2-3" ROLE="Arg-1">
      <extent>
        <charseq START="748" END="818">the south of the country, where a civil war
has been waged for 20 years</charseq>
      </extent>
    </relation_mention_argument>
    <relation_mention_argument REFID="APW_ENG_20030510.0228-E22-4" ROLE="Arg-2">
      <extent>
        <charseq START="761" END="771">the country</charseq>
      </extent>
    </relation_mention_argument>
  </relation_mention>
</relation>
<relation ID="APW_ENG_20030510.0228-R6" TYPE="GEN-AFF" SUBTYPE="Org-Location" TENSE="Unspecified" MODALITY="Asserted">
  <relation_argument REFID="APW_ENG_20030510.0228-E1" ROLE="Arg-1"/>
  <relation_argument REFID="APW_ENG_20030510.0228-E22" ROLE="Arg-2"/>
  <relation_mention ID="APW_ENG_20030510.0228-R6-1" LEXICALCONDITION="Preposition">
    <extent>
      <charseq START="669" END="708">the only English language daily in Sudan</charseq>
    </extent>
    <relation_mention_argument REFID="APW_ENG_20030510.0228-E1-68" ROLE="Arg-1">
      <extent>
        <charseq START="669" END="708">the only English language daily in Sudan</charseq>
      </extent>
    </relation_mention_argument>
    <relation_mention_argument REFID="APW_ENG_20030510.0228-E22-70" ROLE="Arg-2">
      <extent>
        <charseq START="704" END="708">Sudan</charseq>
      </extent>
    </relation_mention_argument>
  </relation_mention>
</relation>
<relation ID="APW_ENG_20030510.0228-R7" TYPE="ORG-AFF" SUBTYPE="Membership" TENSE="Unspecified" MODALITY="Asserted">
  <relation_argument REFID="APW_ENG_20030510.0228-E6" ROLE="Arg-1"/>
  <relation_argument REFID="APW_ENG_20030510.0228-E4" ROLE="Arg-2"/>
  <relation_mention ID="APW_ENG_20030510.0228-R7-1" LEXICALCONDITION="Preposition">
    <extent>
      <charseq START="1059" END="1109">The secretary general of the National Press Council</charseq>
    </extent>
    <relation_mention_argument REFID="APW_ENG_20030510.0228-E6-14" ROLE="Arg-1">
      <extent>
        <charseq START="1059" END="1109">The secretary general of the National Press Council</charseq>
      </extent>
    </relation_mention_argument>
    <relation_mention_argument REFID="APW_ENG_20030510.0228-E4-15" ROLE="Arg-2">
      <extent>
        <charseq START="1084" END="1109">the National Press Council</charseq>
      </extent>
    </relation_mention_argument>
  </relation_mention>
</relation>
<relation ID="APW_ENG_20030510.0228-R8" TYPE="ORG-AFF" SUBTYPE="Employment" TENSE="Unspecified" MODALITY="Asserted">
  <relation_argument REFID="APW_ENG_20030510.0228-E10" ROLE="Arg-1"/>
  <relation_argument REFID="APW_ENG_20030510.0228-E1" ROLE="Arg-2"/>
  <relation_mention ID="APW_ENG_20030510.0228-R8-1" LEXICALCONDITION="Possessive">
    <extent>
      <charseq START="1573" END="1601">the Monitor's managing
editor</charseq>
    </extent>
    <relation_mention_argument REFID="APW_ENG_20030510.0228-E10-24" ROLE="Arg-1">
      <extent>
        <charseq START="1573" END="1601">the Monitor's managing
editor</charseq>
      </extent>
    </relation_mention_argument>
    <relation_mention_argument REFID="APW_ENG_20030510.0228-E1-23" ROLE="Arg-2">
      <extent>
        <charseq START="1573" END="1583">the Monitor</charseq>
      </extent>
    </relation_mention_argument>
  </relation_mention>
</relation>
<relation ID="APW_ENG_20030510.0228-R9" TYPE="ART" SUBTYPE="User-Owner-Inventor-Manufacturer" TENSE="Unspecified" MODALITY="Asserted">
  <relation_argument REFID="APW_ENG_20030510.0228-E1" ROLE="Arg-1"/>
  <relation_argument REFID="APW_ENG_20030510.0228-E14" ROLE="Arg-2"/>
  <relation_mention ID="APW_ENG_20030510.0228-R9-1" LEXICALCONDITION="Possessive">
    <extent>
      <charseq START="1874" END="1894">its editorial offices</charseq>
    </extent>
    <relation_mention_argument REFID="APW_ENG_20030510.0228-E1-33" ROLE="Arg-1">
      <extent>
        <charseq START="1874" END="1876">its</charseq>
      </extent>
    </relation_mention_argument>
    <relation_mention_argument REFID="APW_ENG_20030510.0228-E14-34" ROLE="Arg-2">
      <extent>
        <charseq START="1874" END="1894">its editorial offices</charseq>
      </extent>
    </relation_mention_argument>
  </relation_mention>
  <relation_mention ID="APW_ENG_20030510.0228-R9-2" LEXICALCONDITION="Possessive">
    <extent>
      <charseq START="2126" END="2136">its offices</charseq>
    </extent>
    <relation_mention_argument REFID="APW_ENG_20030510.0228-E1-39" ROLE="Arg-1">
      <extent>
        <charseq START="2126" END="2128">its</charseq>
      </extent>
    </relation_mention_argument>
    <relation_mention_argument REFID="APW_ENG_20030510.0228-E14-40" ROLE="Arg-2">
      <extent>
        <charseq START="2126" END="2136">its offices</charseq>
      </extent>
    </relation_mention_argument>
  </relation_mention>
</relation>
<relation ID="APW_ENG_20030510.0228-R10" TYPE="PHYS" SUBTYPE="Located" TENSE="Unspecified" MODALITY="Asserted">
  <relation_argument REFID="APW_ENG_20030510.0228-E13" ROLE="Arg-1"/>
  <relation_argument REFID="APW_ENG_20030510.0228-E14" ROLE="Arg-2"/>
  <relation_argument REFID="APW_ENG_20030510.0228-T7" ROLE="Time-Within"/>
  <relation_mention ID="APW_ENG_20030510.0228-R10-1" LEXICALCONDITION="Verbal">
    <extent>
      <charseq START="1805" END="2084">In a separate action against the Monitor, security officials went to
its editorial offices on Thursday night and told the management that
it was being closed until it paid a fine of 15 million Sudanese
pounds (about US$6,000) that was outstanding from a court conviction
last year</charseq>
    </extent>
    <relation_mention_argument REFID="APW_ENG_20030510.0228-E13-32" ROLE="Arg-1">
      <extent>
        <charseq START="1847" END="1864">security officials</charseq>
      </extent>
    </relation_mention_argument>
    <relation_mention_argument REFID="APW_ENG_20030510.0228-E14-34" ROLE="Arg-2">
      <extent>
        <charseq START="1874" END="1894">its editorial offices</charseq>
      </extent>
    </relation_mention_argument>
    <relation_mention_argument REFID="APW_ENG_20030510.0228-T7-1" ROLE="Time-Within">
      <extent>
        <charseq START="1899" END="1912">Thursday night</charseq>
      </extent>
    </relation_mention_argument>
  </relation_mention>
</relation>
<relation ID="APW_ENG_20030510.0228-R11" TYPE="GEN-AFF" SUBTYPE="Citizen-Resident-Religion-Ethnicity" TENSE="Unspecified" MODALITY="Asserted">
  <relation_argument REFID="APW_ENG_20030510.0228-E12" ROLE="Arg-1"/>
  <relation_argument REFID="APW_ENG_20030510.0228-E22" ROLE="Arg-2"/>
  <relation_mention ID="APW_ENG_20030510.0228-R11-1" LEXICALCONDITION="Verbal">
    <extent>
      <charseq START="1723" END="1801">Sudan has an Islamic-orientated government and a substantial
Christian minority</charseq>
    </extent>
    <relation_mention_argument REFID="APW_ENG_20030510.0228-E12-30" ROLE="Arg-1">
      <extent>
        <charseq START="1770" END="1801">a substantial
Christian minority</charseq>
      </extent>
    </relation_mention_argument>
    <relation_mention_argument REFID="APW_ENG_20030510.0228-E22-29" ROLE="Arg-2">
      <extent>
        <charseq START="1723" END="1727">Sudan</charseq>
      </extent>
    </relation_mention_argument>
  </relation_mention>
</relation>
<event ID="APW_ENG_20030510.0228-EV1" TYPE="Justice" SUBTYPE="Convict" MODALITY="Asserted" POLARITY="Positive" GENERICITY="Specific" TENSE="Past">
  <event_argument REFID="APW_ENG_20030510.0228-E1" ROLE="Defendant"/>
  <event_argument REFID="APW_ENG_20030510.0228-V7" ROLE="Crime"/>
  <event_argument REFID="APW_ENG_20030510.0228-E3" ROLE="Adjudicator"/>
  <event_argument REFID="APW_ENG_20030510.0228-T13" ROLE="Time-Within"/>
  <event_argument REFID="APW_ENG_20030510.0228-V8" ROLE="Crime"/>
  <event_mention ID="APW_ENG_20030510.0228-EV1-1">
    <extent>
      <charseq START="163" END="310">A state security court suspended a newspaper critical of the
government Saturday after convicting it of publishing religiously
inflammatory material</charseq>
    </extent>
    <ldc_scope>
      <charseq START="163" END="339">A state security court suspended a newspaper critical of the
government Saturday after convicting it of publishing religiously
inflammatory material, the newspaper's lawyer said</charseq>
    </ldc_scope>
    <anchor>
      <charseq START="250" END="259">convicting</charseq>
    </anchor>
    <event_mention_argument REFID="APW_ENG_20030510.0228-E1-61" ROLE="Defendant">
      <extent>
        <charseq START="261" END="262">it</charseq>
      </extent>
    </event_mention_argument>
    <event_mention_argument REFID="APW_ENG_20030510.0228-V7-1" ROLE="Crime">
      <extent>
        <charseq START="267" END="310">publishing religiously
inflammatory material</charseq>
      </extent>
    </event_mention_argument>
    <event_mention_argument REFID="APW_ENG_20030510.0228-E3-59" ROLE="Adjudicator">
      <extent>
        <charseq START="163" END="184">A state security court</charseq>
      </extent>
    </event_mention_argument>
    <event_mention_argument REFID="APW_ENG_20030510.0228-T13-1" ROLE="Time-Within">
      <extent>
        <charseq START="235" END="242">Saturday</charseq>
      </extent>
    </event_mention_argument>
  </event_mention>
  <event_mention ID="APW_ENG_20030510.0228-EV1-2">
    <extent>
      <charseq START="1190" END="1259">The court convicted the paper of violating article 25 of the Press
Law</charseq>
    </extent>
    <ldc_scope>
      <charseq START="1190" END="1371">The court convicted the paper of violating article 25 of the Press
Law, which prohibits the publication of material that defames
religion or incites religiously unacceptable activity</charseq>
    </ldc_scope>
    <anchor>
      <charseq START="1200" END="1208">convicted</charseq>
    </anchor>
    <event_mention_argument REFID="APW_ENG_20030510.0228-E3-19" ROLE="Adjudicator">
      <extent>
        <charseq START="1190" END="1198">The court</charseq>
      </extent>
    </event_mention_argument>
    <event_mention_argument REFID="APW_ENG_20030510.0228-V8-1" ROLE="Crime">
      <extent>
        <charseq START="1223" END="1259">violating article 25 of the Press
Law</charseq>
      </extent>
    </event_mention_argument>
    <event_mention_argument REFID="APW_ENG_20030510.0228-E1-20" ROLE="Defendant">
      <extent>
        <charseq START="1210" END="1218">the paper</charseq>
      </extent>
    </event_mention_argument>
  </event_mention>
</event>
<event ID="APW_ENG_20030510.0228-EV2" TYPE="Justice" SUBTYPE="Fine" MODALITY="Asserted" POLARITY="Positive" GENERICITY="Specific" TENSE="Unspecified">
  <event_argument REFID="APW_ENG_20030510.0228-E1" ROLE="Entity"/>
  <event_argument REFID="APW_ENG_20030510.0228-V1" ROLE="Money"/>
  <event_mention ID="APW_ENG_20030510.0228-EV2-1">
    <extent>
      <charseq START="343" END="441">The Khartoum Monitor may not appear for two months and must pay a
fine of 1 million Sudanese pounds</charseq>
    </extent>
    <ldc_scope>
      <charseq START="343" END="506">The Khartoum Monitor may not appear for two months and must pay a
fine of 1 million Sudanese pounds (about US$400), lawyer Ngor Olang
Ngor told The Associated Press</charseq>
    </ldc_scope>
    <anchor>
      <charseq START="409" END="412">fine</charseq>
    </anchor>
    <event_mention_argument REFID="APW_ENG_20030510.0228-E1-63" ROLE="Entity">
      <extent>
        <charseq START="343" END="362">The Khartoum Monitor</charseq>
      </extent>
    </event_mention_argument>
    <event_mention_argument REFID="APW_ENG_20030510.0228-V1-1" ROLE="Money">
      <extent>
        <charseq START="417" END="441">1 million Sudanese pounds</charseq>
      </extent>
    </event_mention_argument>
  </event_mention>
  <event_mention ID="APW_ENG_20030510.0228-EV2-2">
    <extent>
      <charseq START="832" END="859">the paper would pay the fine</charseq>
    </extent>
    <ldc_scope>
      <charseq START="822" END="896">Ngor said the paper would pay the fine but it would also appeal the
verdict</charseq>
    </ldc_scope>
    <anchor>
      <charseq START="856" END="859">fine</charseq>
    </anchor>
    <event_mention_argument REFID="APW_ENG_20030510.0228-E1-7" ROLE="Entity">
      <extent>
        <charseq START="832" END="840">the paper</charseq>
      </extent>
    </event_mention_argument>
  </event_mention>
  <event_mention ID="APW_ENG_20030510.0228-EV2-3">
    <extent>
      <charseq START="528" END="531">fine</charseq>
    </extent>
    <ldc_scope>
      <charseq START="509" END="587">Failure to pay the fine would result
in a two-month extension of the suspension</charseq>
    </ldc_scope>
    <anchor>
      <charseq START="528" END="531">fine</charseq>
    </anchor>
  </event_mention>
</event>
<event ID="APW_ENG_20030510.0228-EV3" TYPE="Conflict" SUBTYPE="Attack" MODALITY="Asserted" POLARITY="Positive" GENERICITY="Specific" TENSE="Unspecified">
  <event_argument REFID="APW_ENG_20030510.0228-E2" ROLE="Place"/>
  <event_argument REFID="APW_ENG_20030510.0228-T2" ROLE="Time-Holds"/>
  <event_mention ID="APW_ENG_20030510.0228-EV3-1">
    <extent>
      <charseq START="748" END="818">the south of the country, where a civil war
has been waged for 20 years</charseq>
    </extent>
    <ldc_scope>
      <charseq START="591" END="818">The sentence was the latest in a series of state actions against the
Monitor, the only English language daily in Sudan and a leading
critic of conditions in the south of the country, where a civil war
has been waged for 20 years</charseq>
    </ldc_scope>
    <anchor>
      <charseq START="788" END="790">war</charseq>
    </anchor>
    <event_mention_argument REFID="APW_ENG_20030510.0228-E2-3" ROLE="Place">
      <extent>
        <charseq START="748" END="818">the south of the country, where a civil war
has been waged for 20 years</charseq>
      </extent>
    </event_mention_argument>
    <event_mention_argument REFID="APW_ENG_20030510.0228-T2-1" ROLE="Time-Holds">
      <extent>
        <charseq START="811" END="818">20 years</charseq>
      </extent>
    </event_mention_argument>
  </event_mention>
</event>
<event ID="APW_ENG_20030510.0228-EV4" TYPE="Justice" SUBTYPE="Sentence" MODALITY="Asserted" POLARITY="Positive" GENERICITY="Specific" TENSE="Past">
  <event_argument REFID="APW_ENG_20030510.0228-E3" ROLE="Adjudicator"/>
  <event_argument REFID="APW_ENG_20030510.0228-E22" ROLE="Adjudicator"/>
  <event_argument REFID="APW_ENG_20030510.0228-E1" ROLE="Defendant"/>
  <event_mention ID="APW_ENG_20030510.0228-EV4-1">
    <extent>
      <charseq START="595" END="666">sentence was the latest in a series of state actions against the
Monitor</charseq>
    </extent>
    <ldc_scope>
      <charseq START="591" END="818">The sentence was the latest in a series of state actions against the
Monitor, the only English language daily in Sudan and a leading
critic of conditions in the south of the country, where a civil war
has been waged for 20 years</charseq>
    </ldc_scope>
    <anchor>
      <charseq START="595" END="602">sentence</charseq>
    </anchor>
    <event_mention_argument REFID="APW_ENG_20030510.0228-E22-49" ROLE="Adjudicator">
      <extent>
        <charseq START="634" END="638">state</charseq>
      </extent>
    </event_mention_argument>
    <event_mention_argument REFID="APW_ENG_20030510.0228-E1-67" ROLE="Defendant">
      <extent>
        <charseq START="656" END="666">the
Monitor</charseq>
      </extent>
    </event_mention_argument>
  </event_mention>
  <event_mention ID="APW_ENG_20030510.0228-EV4-2">
    <extent>
      <charseq START="904" END="952">court ruling stated that the verdict and sentence</charseq>
    </extent>
    <ldc_scope>
      <charseq START="900" END="1055">The court ruling stated that the verdict and sentence would be
submitted to the National Press Council, a government-appointed body,
for approval, Ngor said</charseq>
    </ldc_scope>
    <anchor>
      <charseq START="945" END="952">sentence</charseq>
    </anchor>
    <event_mention_argument REFID="APW_ENG_20030510.0228-E3-9" ROLE="Adjudicator">
      <extent>
        <charseq START="904" END="908">court</charseq>
      </extent>
    </event_mention_argument>
  </event_mention>
</event>
<event ID="APW_ENG_20030510.0228-EV5" TYPE="Justice" SUBTYPE="Charge-Indict" MODALITY="Asserted" POLARITY="Positive" GENERICITY="Specific" TENSE="Unspecified">
  <event_mention ID="APW_ENG_20030510.0228-EV5-1">
    <extent>
      <charseq START="1379" END="1385">charges</charseq>
    </extent>
    <ldc_scope>
      <charseq START="1375" END="1464">The charges arose from letters-to-the-editor published last month
that dealt with religion</charseq>
    </ldc_scope>
    <anchor>
      <charseq START="1379" END="1385">charges</charseq>
    </anchor>
  </event_mention>
</event>
<event ID="APW_ENG_20030510.0228-EV6" TYPE="Justice" SUBTYPE="Arrest-Jail" MODALITY="Asserted" POLARITY="Positive" GENERICITY="Specific" TENSE="Past">
  <event_argument REFID="APW_ENG_20030510.0228-E10" ROLE="Person"/>
  <event_argument REFID="APW_ENG_20030510.0228-E9" ROLE="Agent"/>
  <event_argument REFID="APW_ENG_20030510.0228-T5" ROLE="Time-Within"/>
  <event_argument REFID="APW_ENG_20030510.0228-T6" ROLE="Time-Holds"/>
  <event_mention ID="APW_ENG_20030510.0228-EV6-1">
    <extent>
      <charseq START="1529" END="1626">Earlier this week, security police detained the Monitor's managing
editor, Nhial Bol, for 24 hours</charseq>
    </extent>
    <ldc_scope>
      <charseq START="1529" END="1626">Earlier this week, security police detained the Monitor's managing
editor, Nhial Bol, for 24 hours</charseq>
    </ldc_scope>
    <anchor>
      <charseq START="1564" END="1571">detained</charseq>
    </anchor>
    <event_mention_argument REFID="APW_ENG_20030510.0228-E10-24" ROLE="Person">
      <extent>
        <charseq START="1573" END="1601">the Monitor's managing
editor</charseq>
      </extent>
    </event_mention_argument>
    <event_mention_argument REFID="APW_ENG_20030510.0228-E9-22" ROLE="Agent">
      <extent>
        <charseq START="1548" END="1562">security police</charseq>
      </extent>
    </event_mention_argument>
    <event_mention_argument REFID="APW_ENG_20030510.0228-T5-1" ROLE="Time-Within">
      <extent>
        <charseq START="1529" END="1545">Earlier this week</charseq>
      </extent>
    </event_mention_argument>
    <event_mention_argument REFID="APW_ENG_20030510.0228-T6-1" ROLE="Time-Holds">
      <extent>
        <charseq START="1619" END="1626">24 hours</charseq>
      </extent>
    </event_mention_argument>
  </event_mention>
</event>
<event ID="APW_ENG_20030510.0228-EV7" TYPE="Justice" SUBTYPE="Release-Parole" MODALITY="Asserted" POLARITY="Positive" GENERICITY="Specific" TENSE="Past">
  <event_argument REFID="APW_ENG_20030510.0228-E10" ROLE="Person"/>
  <event_mention ID="APW_ENG_20030510.0228-EV7-1">
    <extent>
      <charseq START="1632" END="1642">his release</charseq>
    </extent>
    <ldc_scope>
      <charseq START="1629" END="1719">On his release, he was charged with
incitement of public discord for publishing the letters</charseq>
    </ldc_scope>
    <anchor>
      <charseq START="1636" END="1642">release</charseq>
    </anchor>
    <event_mention_argument REFID="APW_ENG_20030510.0228-E10-27" ROLE="Person">
      <extent>
        <charseq START="1632" END="1634">his</charseq>
      </extent>
    </event_mention_argument>
  </event_mention>
</event>
<event ID="APW_ENG_20030510.0228-EV8" TYPE="Justice" SUBTYPE="Charge-Indict" MODALITY="Asserted" POLARITY="Positive" GENERICITY="Specific" TENSE="Past">
  <event_argument REFID="APW_ENG_20030510.0228-E10" ROLE="Defendant"/>
  <event_argument REFID="APW_ENG_20030510.0228-V5" ROLE="Crime"/>
  <event_mention ID="APW_ENG_20030510.0228-EV8-1">
    <extent>
      <charseq START="1645" END="1692">he was charged with
incitement of public discord</charseq>
    </extent>
    <ldc_scope>
      <charseq START="1629" END="1719">On his release, he was charged with
incitement of public discord for publishing the letters</charseq>
    </ldc_scope>
    <anchor>
      <charseq START="1652" END="1658">charged</charseq>
    </anchor>
    <event_mention_argument REFID="APW_ENG_20030510.0228-E10-28" ROLE="Defendant">
      <extent>
        <charseq START="1645" END="1646">he</charseq>
      </extent>
    </event_mention_argument>
    <event_mention_argument REFID="APW_ENG_20030510.0228-V5-1" ROLE="Crime">
      <extent>
        <charseq START="1665" END="1692">incitement of public discord</charseq>
      </extent>
    </event_mention_argument>
  </event_mention>
</event>
<event ID="APW_ENG_20030510.0228-EV9" TYPE="Justice" SUBTYPE="Fine" MODALITY="Asserted" POLARITY="Positive" GENERICITY="Specific" TENSE="Past">
  <event_argument REFID="APW_ENG_20030510.0228-E1" ROLE="Entity"/>
  <event_argument REFID="APW_ENG_20030510.0228-V3" ROLE="Money"/>
  <event_argument REFID="APW_ENG_20030510.0228-E14" ROLE="Place"/>
  <event_argument REFID="APW_ENG_20030510.0228-T7" ROLE="Time-Within"/>
  <event_mention ID="APW_ENG_20030510.0228-EV9-1">
    <extent>
      <charseq START="1834" END="2012">the Monitor, security officials went to
its editorial offices on Thursday night and told the management that
it was being closed until it paid a fine of 15 million Sudanese
pounds</charseq>
    </extent>
    <ldc_scope>
      <charseq START="1805" END="2084">In a separate action against the Monitor, security officials went to
its editorial offices on Thursday night and told the management that
it was being closed until it paid a fine of 15 million Sudanese
pounds (about US$6,000) that was outstanding from a court conviction
last year</charseq>
    </ldc_scope>
    <anchor>
      <charseq START="1979" END="1982">fine</charseq>
    </anchor>
    <event_mention_argument REFID="APW_ENG_20030510.0228-E1-31" ROLE="Entity">
      <extent>
        <charseq START="1834" END="1844">the Monitor</charseq>
      </extent>
    </event_mention_argument>
    <event_mention_argument REFID="APW_ENG_20030510.0228-V3-1" ROLE="Money">
      <extent>
        <charseq START="1987" END="2012">15 million Sudanese
pounds</charseq>
      </extent>
    </event_mention_argument>
    <event_mention_argument REFID="APW_ENG_20030510.0228-E14-34" ROLE="Place">
      <extent>
        <charseq START="1874" END="1894">its editorial offices</charseq>
      </extent>
    </event_mention_argument>
    <event_mention_argument REFID="APW_ENG_20030510.0228-T7-1" ROLE="Time-Within">
      <extent>
        <charseq START="1899" END="1912">Thursday night</charseq>
      </extent>
    </event_mention_argument>
  </event_mention>
</event>
<event ID="APW_ENG_20030510.0228-EV10" TYPE="Justice" SUBTYPE="Convict" MODALITY="Asserted" POLARITY="Positive" GENERICITY="Specific" TENSE="Past">
  <event_argument REFID="APW_ENG_20030510.0228-E1" ROLE="Defendant"/>
  <event_argument REFID="APW_ENG_20030510.0228-V6" ROLE="Crime"/>
  <event_argument REFID="APW_ENG_20030510.0228-T10" ROLE="Time-Within"/>
  <event_argument REFID="APW_ENG_20030510.0228-E15" ROLE="Adjudicator"/>
  <event_mention ID="APW_ENG_20030510.0228-EV10-1">
    <extent>
      <charseq START="1969" END="2074">it paid a fine of 15 million Sudanese
pounds (about US$6,000) that was outstanding from a court conviction</charseq>
    </extent>
    <ldc_scope>
      <charseq START="1805" END="2084">In a separate action against the Monitor, security officials went to
its editorial offices on Thursday night and told the management that
it was being closed until it paid a fine of 15 million Sudanese
pounds (about US$6,000) that was outstanding from a court conviction
last year</charseq>
    </ldc_scope>
    <anchor>
      <charseq START="2065" END="2074">conviction</charseq>
    </anchor>
    <event_mention_argument REFID="APW_ENG_20030510.0228-E1-36" ROLE="Defendant">
      <extent>
        <charseq START="1969" END="1970">it</charseq>
      </extent>
    </event_mention_argument>
    <event_mention_argument REFID="APW_ENG_20030510.0228-E15-37" ROLE="Adjudicator">
      <extent>
        <charseq START="2059" END="2063">court</charseq>
      </extent>
    </event_mention_argument>
  </event_mention>
  <event_mention ID="APW_ENG_20030510.0228-EV10-2">
    <extent>
      <charseq START="2155" END="2223">last year's trial, the paper was convicted of defaming the
government</charseq>
    </extent>
    <ldc_scope>
      <charseq START="2152" END="2336">In last year's trial, the paper was convicted of defaming the
government for publishing that trains running to and from southern
Sudan were used to transport abducted women and children</charseq>
    </ldc_scope>
    <anchor>
      <charseq START="2188" END="2196">convicted</charseq>
    </anchor>
    <event_mention_argument REFID="APW_ENG_20030510.0228-E1-41" ROLE="Defendant">
      <extent>
        <charseq START="2174" END="2182">the paper</charseq>
      </extent>
    </event_mention_argument>
    <event_mention_argument REFID="APW_ENG_20030510.0228-V6-1" ROLE="Crime">
      <extent>
        <charseq START="2201" END="2223">defaming the
government</charseq>
      </extent>
    </event_mention_argument>
    <event_mention_argument REFID="APW_ENG_20030510.0228-T10-1" ROLE="Time-Within">
      <extent>
        <charseq START="2155" END="2163">last year</charseq>
      </extent>
    </event_mention_argument>
  </event_mention>
</event>
<event ID="APW_ENG_20030510.0228-EV11" TYPE="Justice" SUBTYPE="Trial-Hearing" MODALITY="Asserted" POLARITY="Positive" GENERICITY="Specific" TENSE="Past">
  <event_argument REFID="APW_ENG_20030510.0228-E1" ROLE="Defendant"/>
  <event_argument REFID="APW_ENG_20030510.0228-T10" ROLE="Time-Within"/>
  <event_mention ID="APW_ENG_20030510.0228-EV11-1">
    <extent>
      <charseq START="2155" END="2182">last year's trial, the paper</charseq>
    </extent>
    <ldc_scope>
      <charseq START="2152" END="2336">In last year's trial, the paper was convicted of defaming the
government for publishing that trains running to and from southern
Sudan were used to transport abducted women and children</charseq>
    </ldc_scope>
    <anchor>
      <charseq START="2167" END="2171">trial</charseq>
    </anchor>
    <event_mention_argument REFID="APW_ENG_20030510.0228-E1-41" ROLE="Defendant">
      <extent>
        <charseq START="2174" END="2182">the paper</charseq>
      </extent>
    </event_mention_argument>
    <event_mention_argument REFID="APW_ENG_20030510.0228-T10-1" ROLE="Time-Within">
      <extent>
        <charseq START="2155" END="2163">last year</charseq>
      </extent>
    </event_mention_argument>
  </event_mention>
</event>
<event ID="APW_ENG_20030510.0228-EV12" TYPE="Movement" SUBTYPE="Transport" MODALITY="Asserted" POLARITY="Positive" GENERICITY="Generic" TENSE="Past">
  <event_argument REFID="APW_ENG_20030510.0228-E16" ROLE="Vehicle"/>
  <event_argument REFID="APW_ENG_20030510.0228-E19" ROLE="Artifact"/>
  <event_argument REFID="APW_ENG_20030510.0228-E20" ROLE="Artifact"/>
  <event_argument REFID="APW_ENG_20030510.0228-E18" ROLE="Destination"/>
  <event_argument REFID="APW_ENG_20030510.0228-E18" ROLE="Origin"/>
  <event_mention ID="APW_ENG_20030510.0228-EV12-1">
    <extent>
      <charseq START="2245" END="2336">trains running to and from southern
Sudan were used to transport abducted women and children</charseq>
    </extent>
    <ldc_scope>
      <charseq START="2152" END="2336">In last year's trial, the paper was convicted of defaming the
government for publishing that trains running to and from southern
Sudan were used to transport abducted women and children</charseq>
    </ldc_scope>
    <anchor>
      <charseq START="2300" END="2308">transport</charseq>
    </anchor>
    <event_mention_argument REFID="APW_ENG_20030510.0228-E16-42" ROLE="Vehicle">
      <extent>
        <charseq START="2245" END="2285">trains running to and from southern
Sudan</charseq>
      </extent>
    </event_mention_argument>
    <event_mention_argument REFID="APW_ENG_20030510.0228-E19-44" ROLE="Artifact">
      <extent>
        <charseq START="2310" END="2336">abducted women and children</charseq>
      </extent>
    </event_mention_argument>
    <event_mention_argument REFID="APW_ENG_20030510.0228-E20-45" ROLE="Artifact">
      <extent>
        <charseq START="2310" END="2336">abducted women and children</charseq>
      </extent>
    </event_mention_argument>
    <event_mention_argument REFID="APW_ENG_20030510.0228-E18-43" ROLE="Destination">
      <extent>
        <charseq START="2272" END="2285">southern
Sudan</charseq>
      </extent>
    </event_mention_argument>
    <event_mention_argument REFID="APW_ENG_20030510.0228-E18-43" ROLE="Origin">
      <extent>
        <charseq START="2272" END="2285">southern
Sudan</charseq>
      </extent>
    </event_mention_argument>
  </event_mention>
</event>
<event ID="APW_ENG_20030510.0228-EV13" TYPE="Justice" SUBTYPE="Appeal" MODALITY="Asserted" POLARITY="Positive" GENERICITY="Specific" TENSE="Future">
  <event_argument REFID="APW_ENG_20030510.0228-E1" ROLE="Plaintiff"/>
  <event_mention ID="APW_ENG_20030510.0228-EV13-1">
    <extent>
      <charseq START="832" END="884">the paper would pay the fine but it would also appeal</charseq>
    </extent>
    <ldc_scope>
      <charseq START="822" END="896">Ngor said the paper would pay the fine but it would also appeal the
verdict</charseq>
    </ldc_scope>
    <anchor>
      <charseq START="879" END="884">appeal</charseq>
    </anchor>
    <event_mention_argument REFID="APW_ENG_20030510.0228-E1-7" ROLE="Plaintiff">
      <extent>
        <charseq START="832" END="840">the paper</charseq>
      </extent>
    </event_mention_argument>
  </event_mention>
</event>
<event ID="APW_ENG_20030510.0228-EV14" TYPE="Movement" SUBTYPE="Transport" MODALITY="Asserted" POLARITY="Positive" GENERICITY="Specific" TENSE="Past">
  <event_argument REFID="APW_ENG_20030510.0228-E13" ROLE="Artifact"/>
  <event_argument REFID="APW_ENG_20030510.0228-E14" ROLE="Destination"/>
  <event_argument REFID="APW_ENG_20030510.0228-T7" ROLE="Time-Within"/>
  <event_mention ID="APW_ENG_20030510.0228-EV14-1">
    <extent>
      <charseq START="1847" END="1912">security officials went to
its editorial offices on Thursday night</charseq>
    </extent>
    <ldc_scope>
      <charseq START="1805" END="2084">In a separate action against the Monitor, security officials went to
its editorial offices on Thursday night and told the management that
it was being closed until it paid a fine of 15 million Sudanese
pounds (about US$6,000) that was outstanding from a court conviction
last year</charseq>
    </ldc_scope>
    <anchor>
      <charseq START="1866" END="1869">went</charseq>
    </anchor>
    <event_mention_argument REFID="APW_ENG_20030510.0228-E13-32" ROLE="Artifact">
      <extent>
        <charseq START="1847" END="1864">security officials</charseq>
      </extent>
    </event_mention_argument>
    <event_mention_argument REFID="APW_ENG_20030510.0228-E14-34" ROLE="Destination">
      <extent>
        <charseq START="1874" END="1894">its editorial offices</charseq>
      </extent>
    </event_mention_argument>
    <event_mention_argument REFID="APW_ENG_20030510.0228-T7-1" ROLE="Time-Within">
      <extent>
        <charseq START="1899" END="1912">Thursday night</charseq>
      </extent>
    </event_mention_argument>
  </event_mention>
</event>
</document>
</source_file>
